[
  {
    "date": "2020-01-01",
    "value": 8.3214
  },
  {
    "date": "2020-01-02",
    "value": 4.9696
  },
  {
    "date": "2020-01-03",
    "value": 9.6192
  },
  {
    "date": "2020-01-04",
    "value": 0.0293
  },
  {
    "date": "2020-01-05",
    "value": 1.231
  },
  {
    "date": "2020-01-06",
    "value": 3.0513
  },
  {
    "date": "2020-01-07",
    "value": 5.2753
  },
  {
    "date": "2020-01-08",
    "value": 9.3965
  },
  {
    "date": "2020-01-09",
    "value": 7.0469
  },
  {
    "date": "2020-01-10",
    "value": 9.7519
  },
  {
    "date": "2020-01-11",
    "value": 7.499
  },
  {
    "date": "2020-01-12",
    "value": 7.0153
  },
  {
    "date": "2020-01-13",
    "value": 7.3862
  },
  {
    "date": "2020-01-14",
    "value": 8.807
  },
  {
    "date": "2020-01-15",
    "value": 6.5226
  },
  {
    "date": "2020-01-16",
    "value": 6.9106
  },
  {
    "date": "2020-01-17",
    "value": 0.8145
  },
  {
    "date": "2020-01-18",
    "value": 7.6113
  },
  {
    "date": "2020-01-19",
    "value": 0.9244
  },
  {
    "date": "2020-01-20",
    "value": 3.3928
  },
  {
    "date": "2020-01-21",
    "value": 4.1087
  },
  {
    "date": "2020-01-22",
    "value": 1.915
  },
  {
    "date": "2020-01-23",
    "value": 7.3677
  },
  {
    "date": "2020-01-24",
    "value": 3.5548
  },
  {
    "date": "2020-01-25",
    "value": 0.9811
  },
  {
    "date": "2020-01-26",
    "value": 1.0081
  },
  {
    "date": "2020-01-27",
    "value": 2.2956
  },
  {
    "date": "2020-01-28",
    "value": 8.5352
  },
  {
    "date": "2020-01-29",
    "value": 3.06
  },
  {
    "date": "2020-01-30",
    "value": 5.639
  },
  {
    "date": "2020-01-31",
    "value": 1.2165
  },
  {
    "date": "2020-02-01",
    "value": 1.2622
  },
  {
    "date": "2020-02-02",
    "value": 0.7298
  },
  {
    "date": "2020-02-03",
    "value": 3.1185
  },
  {
    "date": "2020-02-04",
    "value": 0.4656
  },
  {
    "date": "2020-02-05",
    "value": 0.2369
  },
  {
    "date": "2020-02-06",
    "value": 2.9339
  },
  {
    "date": "2020-02-07",
    "value": 7.1551
  },
  {
    "date": "2020-02-08",
    "value": 1.4648
  },
  {
    "date": "2020-02-09",
    "value": 8.1514
  },
  {
    "date": "2020-02-10",
    "value": 9.9274
  },
  {
    "date": "2020-02-11",
    "value": 4.492
  },
  {
    "date": "2020-02-12",
    "value": 9.492
  },
  {
    "date": "2020-02-13",
    "value": 1.0969
  },
  {
    "date": "2020-02-14",
    "value": 4.5865
  },
  {
    "date": "2020-02-15",
    "value": 8.0726
  },
  {
    "date": "2020-02-16",
    "value": 2.2783
  },
  {
    "date": "2020-02-17",
    "value": 2.4876
  },
  {
    "date": "2020-02-18",
    "value": 5.8096
  },
  {
    "date": "2020-02-19",
    "value": 5.8367
  },
  {
    "date": "2020-02-20",
    "value": 3.4804
  },
  {
    "date": "2020-02-21",
    "value": 7.4241
  },
  {
    "date": "2020-02-22",
    "value": 4.0528
  },
  {
    "date": "2020-02-23",
    "value": 5.9649
  },
  {
    "date": "2020-02-24",
    "value": 1.4717
  },
  {
    "date": "2020-02-25",
    "value": 2.9787
  },
  {
    "date": "2020-02-26",
    "value": 0.0966
  },
  {
    "date": "2020-02-27",
    "value": 0.3967
  },
  {
    "date": "2020-02-28",
    "value": 7.8134
  },
  {
    "date": "2020-02-29",
    "value": 1.1141
  },
  {
    "date": "2020-03-01",
    "value": 0.773
  },
  {
    "date": "2020-03-02",
    "value": 4.5022
  },
  {
    "date": "2020-03-03",
    "value": 3.9318
  },
  {
    "date": "2020-03-04",
    "value": 8.604
  },
  {
    "date": "2020-03-05",
    "value": 5.3324
  },
  {
    "date": "2020-03-06",
    "value": 1.6362
  },
  {
    "date": "2020-03-07",
    "value": 4.4549
  },
  {
    "date": "2020-03-08",
    "value": 2.0191
  },
  {
    "date": "2020-03-09",
    "value": 6.7644
  },
  {
    "date": "2020-03-10",
    "value": 1.6916
  },
  {
    "date": "2020-03-11",
    "value": 5.3647
  },
  {
    "date": "2020-03-12",
    "value": 4.3564
  },
  {
    "date": "2020-03-13",
    "value": 0.7619
  },
  {
    "date": "2020-03-14",
    "value": 2.428
  },
  {
    "date": "2020-03-15",
    "value": 3.1188
  },
  {
    "date": "2020-03-16",
    "value": 5.1261
  },
  {
    "date": "2020-03-17",
    "value": 7.367
  },
  {
    "date": "2020-03-18",
    "value": 2.7833
  },
  {
    "date": "2020-03-19",
    "value": 2.7144
  },
  {
    "date": "2020-03-20",
    "value": 9.8336
  },
  {
    "date": "2020-03-21",
    "value": 3.398
  },
  {
    "date": "2020-03-22",
    "value": 0.4309
  },
  {
    "date": "2020-03-23",
    "value": 7.4694
  },
  {
    "date": "2020-03-24",
    "value": 1.5159
  },
  {
    "date": "2020-03-25",
    "value": 2.7339
  },
  {
    "date": "2020-03-26",
    "value": 9.2833
  },
  {
    "date": "2020-03-27",
    "value": 5.941
  },
  {
    "date": "2020-03-28",
    "value": 1.4247
  },
  {
    "date": "2020-03-29",
    "value": 3.0387
  },
  {
    "date": "2020-03-30",
    "value": 5.0743
  },
  {
    "date": "2020-03-31",
    "value": 0.1028
  },
  {
    "date": "2020-04-01",
    "value": 9.8189
  },
  {
    "date": "2020-04-02",
    "value": 7.9113
  },
  {
    "date": "2020-04-03",
    "value": 0.8351
  },
  {
    "date": "2020-04-04",
    "value": 1.3944
  },
  {
    "date": "2020-04-05",
    "value": 2.044
  },
  {
    "date": "2020-04-06",
    "value": 9.6579
  },
  {
    "date": "2020-04-07",
    "value": 1.0996
  },
  {
    "date": "2020-04-08",
    "value": 4.178
  },
  {
    "date": "2020-04-09",
    "value": 5.7023
  },
  {
    "date": "2020-04-10",
    "value": 8.2985
  },
  {
    "date": "2020-04-11",
    "value": 9.9595
  },
  {
    "date": "2020-04-12",
    "value": 5.2774
  },
  {
    "date": "2020-04-13",
    "value": 7.3654
  },
  {
    "date": "2020-04-14",
    "value": 7.1524
  },
  {
    "date": "2020-04-15",
    "value": 5.7599
  },
  {
    "date": "2020-04-16",
    "value": 6.4614
  },
  {
    "date": "2020-04-17",
    "value": 8.3792
  },
  {
    "date": "2020-04-18",
    "value": 7.5681
  },
  {
    "date": "2020-04-19",
    "value": 2.3141
  },
  {
    "date": "2020-04-20",
    "value": 2.443
  },
  {
    "date": "2020-04-21",
    "value": 8.1366
  },
  {
    "date": "2020-04-22",
    "value": 8.4561
  },
  {
    "date": "2020-04-23",
    "value": 1.8411
  },
  {
    "date": "2020-04-24",
    "value": 0.5782
  },
  {
    "date": "2020-04-25",
    "value": 1.7015
  },
  {
    "date": "2020-04-26",
    "value": 4.6374
  },
  {
    "date": "2020-04-27",
    "value": 3.1307
  },
  {
    "date": "2020-04-28",
    "value": 7.4634
  },
  {
    "date": "2020-04-29",
    "value": 3.2621
  },
  {
    "date": "2020-04-30",
    "value": 2.5847
  },
  {
    "date": "2020-05-01",
    "value": 0.0854
  },
  {
    "date": "2020-05-02",
    "value": 9.8804
  },
  {
    "date": "2020-05-03",
    "value": 6.6183
  },
  {
    "date": "2020-05-04",
    "value": 3.0332
  },
  {
    "date": "2020-05-05",
    "value": 0.86
  },
  {
    "date": "2020-05-06",
    "value": 7.8829
  },
  {
    "date": "2020-05-07",
    "value": 2.3918
  },
  {
    "date": "2020-05-08",
    "value": 0.7378
  },
  {
    "date": "2020-05-09",
    "value": 3.6044
  },
  {
    "date": "2020-05-10",
    "value": 0.8612
  },
  {
    "date": "2020-05-11",
    "value": 2.4299
  },
  {
    "date": "2020-05-12",
    "value": 8.2911
  },
  {
    "date": "2020-05-13",
    "value": 2.752
  },
  {
    "date": "2020-05-14",
    "value": 6.1441
  },
  {
    "date": "2020-05-15",
    "value": 8.9818
  },
  {
    "date": "2020-05-16",
    "value": 7.6099
  },
  {
    "date": "2020-05-17",
    "value": 9.3355
  },
  {
    "date": "2020-05-18",
    "value": 2.8992
  },
  {
    "date": "2020-05-19",
    "value": 9.3033
  },
  {
    "date": "2020-05-20",
    "value": 8.0762
  },
  {
    "date": "2020-05-21",
    "value": 0.4152
  },
  {
    "date": "2020-05-22",
    "value": 5.7719
  },
  {
    "date": "2020-05-23",
    "value": 7.5699
  },
  {
    "date": "2020-05-24",
    "value": 7.6008
  },
  {
    "date": "2020-05-25",
    "value": 6.4153
  },
  {
    "date": "2020-05-26",
    "value": 6.4345
  },
  {
    "date": "2020-05-27",
    "value": 4.8764
  },
  {
    "date": "2020-05-28",
    "value": 8.0149
  },
  {
    "date": "2020-05-29",
    "value": 3.2546
  },
  {
    "date": "2020-05-30",
    "value": 6.4546
  },
  {
    "date": "2020-05-31",
    "value": 4.16
  },
  {
    "date": "2020-06-01",
    "value": 4.7595
  },
  {
    "date": "2020-06-02",
    "value": 8.4461
  },
  {
    "date": "2020-06-03",
    "value": 3.4121
  },
  {
    "date": "2020-06-04",
    "value": 9.3466
  },
  {
    "date": "2020-06-05",
    "value": 9.3069
  },
  {
    "date": "2020-06-06",
    "value": 8.5564
  },
  {
    "date": "2020-06-07",
    "value": 0.5027
  },
  {
    "date": "2020-06-08",
    "value": 6.6472
  },
  {
    "date": "2020-06-09",
    "value": 3.6849
  },
  {
    "date": "2020-06-10",
    "value": 5.293
  },
  {
    "date": "2020-06-11",
    "value": 4.4374
  },
  {
    "date": "2020-06-12",
    "value": 9.7086
  },
  {
    "date": "2020-06-13",
    "value": 6.3156
  },
  {
    "date": "2020-06-14",
    "value": 3.4612
  },
  {
    "date": "2020-06-15",
    "value": 5.1938
  },
  {
    "date": "2020-06-16",
    "value": 9.8148
  },
  {
    "date": "2020-06-17",
    "value": 7.2591
  },
  {
    "date": "2020-06-18",
    "value": 2.7411
  },
  {
    "date": "2020-06-19",
    "value": 9.166
  },
  {
    "date": "2020-06-20",
    "value": 6.962
  },
  {
    "date": "2020-06-21",
    "value": 7.246
  },
  {
    "date": "2020-06-22",
    "value": 7.4068
  },
  {
    "date": "2020-06-23",
    "value": 0.6432
  },
  {
    "date": "2020-06-24",
    "value": 7.9912
  },
  {
    "date": "2020-06-25",
    "value": 8.3282
  },
  {
    "date": "2020-06-26",
    "value": 4.0866
  },
  {
    "date": "2020-06-27",
    "value": 6.4243
  },
  {
    "date": "2020-06-28",
    "value": 5.7466
  },
  {
    "date": "2020-06-29",
    "value": 2.7239
  },
  {
    "date": "2020-06-30",
    "value": 8.0445
  },
  {
    "date": "2020-07-01",
    "value": 4.1742
  },
  {
    "date": "2020-07-02",
    "value": 3.9382
  },
  {
    "date": "2020-07-03",
    "value": 4.0647
  },
  {
    "date": "2020-07-04",
    "value": 0.3251
  },
  {
    "date": "2020-07-05",
    "value": 5.2969
  },
  {
    "date": "2020-07-06",
    "value": 0.4743
  },
  {
    "date": "2020-07-07",
    "value": 2.9892
  },
  {
    "date": "2020-07-08",
    "value": 2.6912
  },
  {
    "date": "2020-07-09",
    "value": 8.2638
  },
  {
    "date": "2020-07-10",
    "value": 5.5505
  },
  {
    "date": "2020-07-11",
    "value": 4.0806
  },
  {
    "date": "2020-07-12",
    "value": 5.5404
  },
  {
    "date": "2020-07-13",
    "value": 8.8023
  },
  {
    "date": "2020-07-14",
    "value": 7.5987
  },
  {
    "date": "2020-07-15",
    "value": 6.5557
  },
  {
    "date": "2020-07-16",
    "value": 2.5597
  },
  {
    "date": "2020-07-17",
    "value": 1.3461
  },
  {
    "date": "2020-07-18",
    "value": 0.3166
  },
  {
    "date": "2020-07-19",
    "value": 6.0124
  },
  {
    "date": "2020-07-20",
    "value": 1.0441
  },
  {
    "date": "2020-07-21",
    "value": 1.4493
  },
  {
    "date": "2020-07-22",
    "value": 1.7513
  },
  {
    "date": "2020-07-23",
    "value": 8.5002
  },
  {
    "date": "2020-07-24",
    "value": 3.6925
  },
  {
    "date": "2020-07-25",
    "value": 8.8222
  },
  {
    "date": "2020-07-26",
    "value": 6.2344
  },
  {
    "date": "2020-07-27",
    "value": 8.0784
  },
  {
    "date": "2020-07-28",
    "value": 9.411
  },
  {
    "date": "2020-07-29",
    "value": 6.1942
  },
  {
    "date": "2020-07-30",
    "value": 5.7687
  },
  {
    "date": "2020-07-31",
    "value": 1.8252
  },
  {
    "date": "2020-08-01",
    "value": 0.4492
  },
  {
    "date": "2020-08-02",
    "value": 1.9993
  },
  {
    "date": "2020-08-03",
    "value": 7.5691
  },
  {
    "date": "2020-08-04",
    "value": 5.553
  },
  {
    "date": "2020-08-05",
    "value": 0.0822
  },
  {
    "date": "2020-08-06",
    "value": 1.0817
  },
  {
    "date": "2020-08-07",
    "value": 3.6822
  },
  {
    "date": "2020-08-08",
    "value": 7.1362
  },
  {
    "date": "2020-08-09",
    "value": 8.9034
  },
  {
    "date": "2020-08-10",
    "value": 7.1422
  },
  {
    "date": "2020-08-11",
    "value": 6.7984
  },
  {
    "date": "2020-08-12",
    "value": 5.133
  },
  {
    "date": "2020-08-13",
    "value": 6.9399
  },
  {
    "date": "2020-08-14",
    "value": 5.1353
  },
  {
    "date": "2020-08-15",
    "value": 8.6829
  },
  {
    "date": "2020-08-16",
    "value": 6.4015
  },
  {
    "date": "2020-08-17",
    "value": 5.1509
  },
  {
    "date": "2020-08-18",
    "value": 7.7842
  },
  {
    "date": "2020-08-19",
    "value": 2.9241
  },
  {
    "date": "2020-08-20",
    "value": 8.642
  },
  {
    "date": "2020-08-21",
    "value": 5.0788
  },
  {
    "date": "2020-08-22",
    "value": 1.2001
  },
  {
    "date": "2020-08-23",
    "value": 7.9948
  },
  {
    "date": "2020-08-24",
    "value": 4.6479
  },
  {
    "date": "2020-08-25",
    "value": 0.9502
  },
  {
    "date": "2020-08-26",
    "value": 3.1174
  },
  {
    "date": "2020-08-27",
    "value": 2.5228
  },
  {
    "date": "2020-08-28",
    "value": 0.4667
  },
  {
    "date": "2020-08-29",
    "value": 5.4873
  },
  {
    "date": "2020-08-30",
    "value": 5.6778
  },
  {
    "date": "2020-08-31",
    "value": 5.0352
  },
  {
    "date": "2020-09-01",
    "value": 6.764
  },
  {
    "date": "2020-09-02",
    "value": 5.5294
  },
  {
    "date": "2020-09-03",
    "value": 2.52
  },
  {
    "date": "2020-09-04",
    "value": 1.6208
  },
  {
    "date": "2020-09-05",
    "value": 1.5098
  },
  {
    "date": "2020-09-06",
    "value": 3.9153
  },
  {
    "date": "2020-09-07",
    "value": 4.7153
  },
  {
    "date": "2020-09-08",
    "value": 3.0847
  },
  {
    "date": "2020-09-09",
    "value": 4.9797
  },
  {
    "date": "2020-09-10",
    "value": 3.6064
  },
  {
    "date": "2020-09-11",
    "value": 3.8745
  },
  {
    "date": "2020-09-12",
    "value": 9.1551
  },
  {
    "date": "2020-09-13",
    "value": 9.7702
  },
  {
    "date": "2020-09-14",
    "value": 0.9175
  },
  {
    "date": "2020-09-15",
    "value": 3.137
  },
  {
    "date": "2020-09-16",
    "value": 2.7271
  },
  {
    "date": "2020-09-17",
    "value": 2.9161
  },
  {
    "date": "2020-09-18",
    "value": 4.4545
  },
  {
    "date": "2020-09-19",
    "value": 5.9281
  },
  {
    "date": "2020-09-20",
    "value": 8.1922
  },
  {
    "date": "2020-09-21",
    "value": 2.7737
  },
  {
    "date": "2020-09-22",
    "value": 7.2055
  },
  {
    "date": "2020-09-23",
    "value": 6.0241
  },
  {
    "date": "2020-09-24",
    "value": 2.4178
  },
  {
    "date": "2020-09-25",
    "value": 7.9781
  },
  {
    "date": "2020-09-26",
    "value": 7.871
  },
  {
    "date": "2020-09-27",
    "value": 5.8301
  },
  {
    "date": "2020-09-28",
    "value": 8.1614
  },
  {
    "date": "2020-09-29",
    "value": 5.9839
  },
  {
    "date": "2020-09-30",
    "value": 6.2919
  },
  {
    "date": "2020-10-01",
    "value": 5.2189
  },
  {
    "date": "2020-10-02",
    "value": 3.3226
  },
  {
    "date": "2020-10-03",
    "value": 9.3994
  },
  {
    "date": "2020-10-04",
    "value": 5.807
  },
  {
    "date": "2020-10-05",
    "value": 3.6786
  },
  {
    "date": "2020-10-06",
    "value": 1.1748
  },
  {
    "date": "2020-10-07",
    "value": 1.6045
  },
  {
    "date": "2020-10-08",
    "value": 5.8812
  },
  {
    "date": "2020-10-09",
    "value": 2.1973
  },
  {
    "date": "2020-10-10",
    "value": 5.9572
  },
  {
    "date": "2020-10-11",
    "value": 7.5479
  },
  {
    "date": "2020-10-12",
    "value": 0.4438
  },
  {
    "date": "2020-10-13",
    "value": 6.462
  },
  {
    "date": "2020-10-14",
    "value": 7.5328
  },
  {
    "date": "2020-10-15",
    "value": 4.05
  },
  {
    "date": "2020-10-16",
    "value": 6.2148
  },
  {
    "date": "2020-10-17",
    "value": 8.4454
  },
  {
    "date": "2020-10-18",
    "value": 4.3607
  },
  {
    "date": "2020-10-19",
    "value": 2.1231
  },
  {
    "date": "2020-10-20",
    "value": 6.5065
  },
  {
    "date": "2020-10-21",
    "value": 1.873
  },
  {
    "date": "2020-10-22",
    "value": 7.3617
  },
  {
    "date": "2020-10-23",
    "value": 9.153
  },
  {
    "date": "2020-10-24",
    "value": 0.655
  },
  {
    "date": "2020-10-25",
    "value": 5.9252
  },
  {
    "date": "2020-10-26",
    "value": 1.7528
  },
  {
    "date": "2020-10-27",
    "value": 5.0897
  },
  {
    "date": "2020-10-28",
    "value": 1.3854
  },
  {
    "date": "2020-10-29",
    "value": 6.8435
  },
  {
    "date": "2020-10-30",
    "value": 0.3482
  },
  {
    "date": "2020-10-31",
    "value": 3.5301
  },
  {
    "date": "2020-11-01",
    "value": 7.0955
  },
  {
    "date": "2020-11-02",
    "value": 8.2622
  },
  {
    "date": "2020-11-03",
    "value": 1.7859
  },
  {
    "date": "2020-11-04",
    "value": 5.0733
  },
  {
    "date": "2020-11-05",
    "value": 9.8361
  },
  {
    "date": "2020-11-06",
    "value": 6.7816
  },
  {
    "date": "2020-11-07",
    "value": 5.1748
  },
  {
    "date": "2020-11-08",
    "value": 2.8422
  },
  {
    "date": "2020-11-09",
    "value": 2.5626
  },
  {
    "date": "2020-11-10",
    "value": 7.1004
  },
  {
    "date": "2020-11-11",
    "value": 5.7201
  },
  {
    "date": "2020-11-12",
    "value": 3.6479
  },
  {
    "date": "2020-11-13",
    "value": 4.1753
  },
  {
    "date": "2020-11-14",
    "value": 7.2531
  },
  {
    "date": "2020-11-15",
    "value": 2.7627
  },
  {
    "date": "2020-11-16",
    "value": 2.0168
  },
  {
    "date": "2020-11-17",
    "value": 1.3731
  },
  {
    "date": "2020-11-18",
    "value": 1.6711
  },
  {
    "date": "2020-11-19",
    "value": 7.8488
  },
  {
    "date": "2020-11-20",
    "value": 3.6403
  },
  {
    "date": "2020-11-21",
    "value": 5.7274
  },
  {
    "date": "2020-11-22",
    "value": 3.7981
  },
  {
    "date": "2020-11-23",
    "value": 4.9653
  },
  {
    "date": "2020-11-24",
    "value": 3.4689
  },
  {
    "date": "2020-11-25",
    "value": 4.6266
  },
  {
    "date": "2020-11-26",
    "value": 9.7872
  },
  {
    "date": "2020-11-27",
    "value": 7.7547
  },
  {
    "date": "2020-11-28",
    "value": 0.0511
  },
  {
    "date": "2020-11-29",
    "value": 7.2755
  },
  {
    "date": "2020-11-30",
    "value": 3.8815
  },
  {
    "date": "2020-12-01",
    "value": 2.8274
  },
  {
    "date": "2020-12-02",
    "value": 7.7808
  },
  {
    "date": "2020-12-03",
    "value": 6.9049
  },
  {
    "date": "2020-12-04",
    "value": 9.7458
  },
  {
    "date": "2020-12-05",
    "value": 3.2114
  },
  {
    "date": "2020-12-06",
    "value": 5.3096
  },
  {
    "date": "2020-12-07",
    "value": 3.9138
  },
  {
    "date": "2020-12-08",
    "value": 2.6737
  },
  {
    "date": "2020-12-09",
    "value": 6.8164
  },
  {
    "date": "2020-12-10",
    "value": 7.9681
  },
  {
    "date": "2020-12-11",
    "value": 6.3329
  },
  {
    "date": "2020-12-12",
    "value": 8.2074
  },
  {
    "date": "2020-12-13",
    "value": 0.1446
  },
  {
    "date": "2020-12-14",
    "value": 5.1168
  },
  {
    "date": "2020-12-15",
    "value": 3.2494
  },
  {
    "date": "2020-12-16",
    "value": 5.8544
  },
  {
    "date": "2020-12-17",
    "value": 9.4198
  },
  {
    "date": "2020-12-18",
    "value": 0.6926
  },
  {
    "date": "2020-12-19",
    "value": 5.3482
  },
  {
    "date": "2020-12-20",
    "value": 5.163
  },
  {
    "date": "2020-12-21",
    "value": 5.8534
  },
  {
    "date": "2020-12-22",
    "value": 7.0715
  },
  {
    "date": "2020-12-23",
    "value": 0.9962
  },
  {
    "date": "2020-12-24",
    "value": 7.5121
  },
  {
    "date": "2020-12-25",
    "value": 8.1352
  },
  {
    "date": "2020-12-26",
    "value": 3.8589
  },
  {
    "date": "2020-12-27",
    "value": 6.5991
  },
  {
    "date": "2020-12-28",
    "value": 6.9833
  },
  {
    "date": "2020-12-29",
    "value": 0.7149
  },
  {
    "date": "2020-12-30",
    "value": 3.2163
  }
]