[
  {
    "date": "2020-01-01",
    "value": -2.8178
  },
  {
    "date": "2020-01-02",
    "value": -1.8198
  },
  {
    "date": "2020-01-03",
    "value": 3.1323
  },
  {
    "date": "2020-01-04",
    "value": 3.2691
  },
  {
    "date": "2020-01-05",
    "value": -2.2705
  },
  {
    "date": "2020-01-06",
    "value": 1.178
  },
  {
    "date": "2020-01-07",
    "value": 2.0508
  },
  {
    "date": "2020-01-08",
    "value": -4.9628
  },
  {
    "date": "2020-01-09",
    "value": 4.7788
  },
  {
    "date": "2020-01-10",
    "value": 2.1605
  },
  {
    "date": "2020-01-11",
    "value": -5.0926
  },
  {
    "date": "2020-01-12",
    "value": 4.765
  },
  {
    "date": "2020-01-13",
    "value": 2.5618
  },
  {
    "date": "2020-01-14",
    "value": -1.2531
  },
  {
    "date": "2020-01-15",
    "value": -3.6693
  },
  {
    "date": "2020-01-16",
    "value": 2.1914
  },
  {
    "date": "2020-01-17",
    "value": 7.2573
  },
  {
    "date": "2020-01-18",
    "value": 2.5001
  },
  {
    "date": "2020-01-19",
    "value": 5.1113
  },
  {
    "date": "2020-01-20",
    "value": 3.8651
  },
  {
    "date": "2020-01-21",
    "value": 2.8842
  },
  {
    "date": "2020-01-22",
    "value": -0.5997
  },
  {
    "date": "2020-01-23",
    "value": 3.6694
  },
  {
    "date": "2020-01-24",
    "value": 0.3883
  },
  {
    "date": "2020-01-25",
    "value": -0.4692
  },
  {
    "date": "2020-01-26",
    "value": 7.2471
  },
  {
    "date": "2020-01-27",
    "value": -7.2449
  },
  {
    "date": "2020-01-28",
    "value": -2.1143
  },
  {
    "date": "2020-01-29",
    "value": -1.6029
  },
  {
    "date": "2020-01-30",
    "value": -7.613
  },
  {
    "date": "2020-01-31",
    "value": 0.1159
  },
  {
    "date": "2020-02-01",
    "value": 0.9759
  },
  {
    "date": "2020-02-02",
    "value": -2.8186
  },
  {
    "date": "2020-02-03",
    "value": 2.7096
  },
  {
    "date": "2020-02-04",
    "value": 5.1935
  },
  {
    "date": "2020-02-05",
    "value": -2.3266
  },
  {
    "date": "2020-02-06",
    "value": -1.4019
  },
  {
    "date": "2020-02-07",
    "value": 7.218
  },
  {
    "date": "2020-02-08",
    "value": 0.3135
  },
  {
    "date": "2020-02-09",
    "value": 6.1912
  },
  {
    "date": "2020-02-10",
    "value": -0.358
  },
  {
    "date": "2020-02-11",
    "value": -6.9018
  },
  {
    "date": "2020-02-12",
    "value": -0.6158
  },
  {
    "date": "2020-02-13",
    "value": -3.0024
  },
  {
    "date": "2020-02-14",
    "value": 0.6988
  },
  {
    "date": "2020-02-15",
    "value": 9.2598
  },
  {
    "date": "2020-02-16",
    "value": 2.065
  },
  {
    "date": "2020-02-17",
    "value": 2.3116
  },
  {
    "date": "2020-02-18",
    "value": 1.0374
  },
  {
    "date": "2020-02-19",
    "value": 0.2278
  },
  {
    "date": "2020-02-20",
    "value": 1.3162
  },
  {
    "date": "2020-02-21",
    "value": -2.7306
  },
  {
    "date": "2020-02-22",
    "value": 0.4002
  },
  {
    "date": "2020-02-23",
    "value": -2.2695
  },
  {
    "date": "2020-02-24",
    "value": -0.7338
  },
  {
    "date": "2020-02-25",
    "value": 3.4622
  },
  {
    "date": "2020-02-26",
    "value": 5.0552
  },
  {
    "date": "2020-02-27",
    "value": -3.3905
  },
  {
    "date": "2020-02-28",
    "value": 0.6071
  },
  {
    "date": "2020-02-29",
    "value": -2.1213
  },
  {
    "date": "2020-03-01",
    "value": -5.6774
  },
  {
    "date": "2020-03-02",
    "value": 3.5622
  },
  {
    "date": "2020-03-03",
    "value": 0.9968
  },
  {
    "date": "2020-03-04",
    "value": -3.2334
  },
  {
    "date": "2020-03-05",
    "value": 7.9439
  },
  {
    "date": "2020-03-06",
    "value": 2.2334
  },
  {
    "date": "2020-03-07",
    "value": 0.568
  },
  {
    "date": "2020-03-08",
    "value": -1.7482
  },
  {
    "date": "2020-03-09",
    "value": -0.8268
  },
  {
    "date": "2020-03-10",
    "value": -0.4401
  },
  {
    "date": "2020-03-11",
    "value": -0.7207
  },
  {
    "date": "2020-03-12",
    "value": -3.9755
  },
  {
    "date": "2020-03-13",
    "value": 4.4918
  },
  {
    "date": "2020-03-14",
    "value": 3.5468
  },
  {
    "date": "2020-03-15",
    "value": 0.0559
  },
  {
    "date": "2020-03-16",
    "value": 0.0183
  },
  {
    "date": "2020-03-17",
    "value": -6.0067
  },
  {
    "date": "2020-03-18",
    "value": 3.4126
  },
  {
    "date": "2020-03-19",
    "value": 1.8856
  },
  {
    "date": "2020-03-20",
    "value": 8.5381
  },
  {
    "date": "2020-03-21",
    "value": 1.8551
  },
  {
    "date": "2020-03-22",
    "value": 0.1339
  },
  {
    "date": "2020-03-23",
    "value": 0.4644
  },
  {
    "date": "2020-03-24",
    "value": -0.2234
  },
  {
    "date": "2020-03-25",
    "value": 2.3987
  },
  {
    "date": "2020-03-26",
    "value": 7.2591
  },
  {
    "date": "2020-03-27",
    "value": -3.4932
  },
  {
    "date": "2020-03-28",
    "value": 4.3346
  },
  {
    "date": "2020-03-29",
    "value": 2.1792
  },
  {
    "date": "2020-03-30",
    "value": 4.352
  },
  {
    "date": "2020-03-31",
    "value": 1.3541
  },
  {
    "date": "2020-04-01",
    "value": 3.9968
  },
  {
    "date": "2020-04-02",
    "value": 3.0248
  },
  {
    "date": "2020-04-03",
    "value": -1.2624
  },
  {
    "date": "2020-04-04",
    "value": 1.2603
  },
  {
    "date": "2020-04-05",
    "value": -4.375
  },
  {
    "date": "2020-04-06",
    "value": -0.1192
  },
  {
    "date": "2020-04-07",
    "value": 1.2433
  },
  {
    "date": "2020-04-08",
    "value": 6.4334
  },
  {
    "date": "2020-04-09",
    "value": 6.3923
  },
  {
    "date": "2020-04-10",
    "value": 2.8938
  },
  {
    "date": "2020-04-11",
    "value": 6.1804
  },
  {
    "date": "2020-04-12",
    "value": -3.125
  },
  {
    "date": "2020-04-13",
    "value": 0.7278
  },
  {
    "date": "2020-04-14",
    "value": 0.4895
  },
  {
    "date": "2020-04-15",
    "value": 3.2253
  },
  {
    "date": "2020-04-16",
    "value": 7.0444
  },
  {
    "date": "2020-04-17",
    "value": 3.139
  },
  {
    "date": "2020-04-18",
    "value": 0.6156
  },
  {
    "date": "2020-04-19",
    "value": -4.9537
  },
  {
    "date": "2020-04-20",
    "value": 1.2445
  },
  {
    "date": "2020-04-21",
    "value": 3.0491
  },
  {
    "date": "2020-04-22",
    "value": -0.156
  },
  {
    "date": "2020-04-23",
    "value": -1.3891
  },
  {
    "date": "2020-04-24",
    "value": 7.0126
  },
  {
    "date": "2020-04-25",
    "value": -0.1414
  },
  {
    "date": "2020-04-26",
    "value": 3.3331
  },
  {
    "date": "2020-04-27",
    "value": 0.7918
  },
  {
    "date": "2020-04-28",
    "value": 1.2861
  },
  {
    "date": "2020-04-29",
    "value": -1.0015
  },
  {
    "date": "2020-04-30",
    "value": -1.767
  },
  {
    "date": "2020-05-01",
    "value": -4.5232
  },
  {
    "date": "2020-05-02",
    "value": -3.9895
  },
  {
    "date": "2020-05-03",
    "value": -0.7363
  },
  {
    "date": "2020-05-04",
    "value": -4.4012
  },
  {
    "date": "2020-05-05",
    "value": -4.929
  },
  {
    "date": "2020-05-06",
    "value": -1.3964
  },
  {
    "date": "2020-05-07",
    "value": 1.2678
  },
  {
    "date": "2020-05-08",
    "value": 1.7085
  },
  {
    "date": "2020-05-09",
    "value": 2.7539
  },
  {
    "date": "2020-05-10",
    "value": -3.4988
  },
  {
    "date": "2020-05-11",
    "value": 0.4188
  },
  {
    "date": "2020-05-12",
    "value": 0.1466
  },
  {
    "date": "2020-05-13",
    "value": 3.8101
  },
  {
    "date": "2020-05-14",
    "value": 2.573
  },
  {
    "date": "2020-05-15",
    "value": 4.3173
  },
  {
    "date": "2020-05-16",
    "value": 2.4663
  },
  {
    "date": "2020-05-17",
    "value": -6.6688
  },
  {
    "date": "2020-05-18",
    "value": 6.4038
  },
  {
    "date": "2020-05-19",
    "value": -6.7181
  },
  {
    "date": "2020-05-20",
    "value": 7.4145
  },
  {
    "date": "2020-05-21",
    "value": 2.0557
  },
  {
    "date": "2020-05-22",
    "value": -0.324
  },
  {
    "date": "2020-05-23",
    "value": 1.0288
  },
  {
    "date": "2020-05-24",
    "value": 3.6348
  },
  {
    "date": "2020-05-25",
    "value": -2.2985
  },
  {
    "date": "2020-05-26",
    "value": 0.1647
  },
  {
    "date": "2020-05-27",
    "value": -0.7024
  },
  {
    "date": "2020-05-28",
    "value": 1.9537
  },
  {
    "date": "2020-05-29",
    "value": 4.4949
  },
  {
    "date": "2020-05-30",
    "value": -0.1712
  },
  {
    "date": "2020-05-31",
    "value": 3.301
  },
  {
    "date": "2020-06-01",
    "value": 6.9661
  },
  {
    "date": "2020-06-02",
    "value": 1.352
  },
  {
    "date": "2020-06-03",
    "value": 5.5417
  },
  {
    "date": "2020-06-04",
    "value": -0.9253
  },
  {
    "date": "2020-06-05",
    "value": 1.9016
  },
  {
    "date": "2020-06-06",
    "value": 5.1797
  },
  {
    "date": "2020-06-07",
    "value": -1.7568
  },
  {
    "date": "2020-06-08",
    "value": 7.0551
  },
  {
    "date": "2020-06-09",
    "value": 6.271
  },
  {
    "date": "2020-06-10",
    "value": -4.0751
  },
  {
    "date": "2020-06-11",
    "value": 5.9379
  },
  {
    "date": "2020-06-12",
    "value": -0.5332
  },
  {
    "date": "2020-06-13",
    "value": 1.9093
  },
  {
    "date": "2020-06-14",
    "value": -0.4026
  },
  {
    "date": "2020-06-15",
    "value": 4.1
  },
  {
    "date": "2020-06-16",
    "value": 2.1748
  },
  {
    "date": "2020-06-17",
    "value": -4.3147
  },
  {
    "date": "2020-06-18",
    "value": -1.7152
  },
  {
    "date": "2020-06-19",
    "value": 2.6222
  },
  {
    "date": "2020-06-20",
    "value": 1.784
  },
  {
    "date": "2020-06-21",
    "value": -1.9333
  },
  {
    "date": "2020-06-22",
    "value": -4.051
  },
  {
    "date": "2020-06-23",
    "value": 0.2972
  },
  {
    "date": "2020-06-24",
    "value": 3.4859
  },
  {
    "date": "2020-06-25",
    "value": 7.2323
  },
  {
    "date": "2020-06-26",
    "value": -6.3445
  },
  {
    "date": "2020-06-27",
    "value": -3.397
  },
  {
    "date": "2020-06-28",
    "value": 0.1326
  },
  {
    "date": "2020-06-29",
    "value": 2.8259
  },
  {
    "date": "2020-06-30",
    "value": -0.0076
  },
  {
    "date": "2020-07-01",
    "value": -5.8536
  },
  {
    "date": "2020-07-02",
    "value": 8.5861
  },
  {
    "date": "2020-07-03",
    "value": -1.1859
  },
  {
    "date": "2020-07-04",
    "value": 5.7386
  },
  {
    "date": "2020-07-05",
    "value": -4.1746
  },
  {
    "date": "2020-07-06",
    "value": 6.3508
  },
  {
    "date": "2020-07-07",
    "value": -2.4763
  },
  {
    "date": "2020-07-08",
    "value": 7.4464
  },
  {
    "date": "2020-07-09",
    "value": 2.3257
  },
  {
    "date": "2020-07-10",
    "value": 2.1577
  },
  {
    "date": "2020-07-11",
    "value": -1.5874
  },
  {
    "date": "2020-07-12",
    "value": 8.207
  },
  {
    "date": "2020-07-13",
    "value": 3.6766
  },
  {
    "date": "2020-07-14",
    "value": 3.2078
  },
  {
    "date": "2020-07-15",
    "value": 1.9067
  },
  {
    "date": "2020-07-16",
    "value": 0.1913
  },
  {
    "date": "2020-07-17",
    "value": -0.5628
  },
  {
    "date": "2020-07-18",
    "value": 5.2724
  },
  {
    "date": "2020-07-19",
    "value": -2.7574
  },
  {
    "date": "2020-07-20",
    "value": -2.7401
  },
  {
    "date": "2020-07-21",
    "value": 7.5754
  },
  {
    "date": "2020-07-22",
    "value": 2.0028
  },
  {
    "date": "2020-07-23",
    "value": -3.3675
  },
  {
    "date": "2020-07-24",
    "value": -2.7819
  },
  {
    "date": "2020-07-25",
    "value": 0.5477
  },
  {
    "date": "2020-07-26",
    "value": 5.9124
  },
  {
    "date": "2020-07-27",
    "value": 4.3509
  },
  {
    "date": "2020-07-28",
    "value": -4.9454
  },
  {
    "date": "2020-07-29",
    "value": 7.3581
  },
  {
    "date": "2020-07-30",
    "value": 4.0115
  },
  {
    "date": "2020-07-31",
    "value": 0.6847
  },
  {
    "date": "2020-08-01",
    "value": -1.9276
  },
  {
    "date": "2020-08-02",
    "value": -3.0926
  },
  {
    "date": "2020-08-03",
    "value": -7.4992
  },
  {
    "date": "2020-08-04",
    "value": -4.68
  },
  {
    "date": "2020-08-05",
    "value": 1.5749
  },
  {
    "date": "2020-08-06",
    "value": 1.2706
  },
  {
    "date": "2020-08-07",
    "value": -1.3697
  },
  {
    "date": "2020-08-08",
    "value": -0.386
  },
  {
    "date": "2020-08-09",
    "value": 2.3377
  },
  {
    "date": "2020-08-10",
    "value": 2.8844
  },
  {
    "date": "2020-08-11",
    "value": 0.1408
  },
  {
    "date": "2020-08-12",
    "value": 3.9434
  },
  {
    "date": "2020-08-13",
    "value": -0.2765
  },
  {
    "date": "2020-08-14",
    "value": -4.4835
  },
  {
    "date": "2020-08-15",
    "value": 8.8416
  },
  {
    "date": "2020-08-16",
    "value": -2.962
  },
  {
    "date": "2020-08-17",
    "value": 2.5273
  },
  {
    "date": "2020-08-18",
    "value": -0.533
  },
  {
    "date": "2020-08-19",
    "value": -1.1606
  },
  {
    "date": "2020-08-20",
    "value": -0.5496
  },
  {
    "date": "2020-08-21",
    "value": 2.2173
  },
  {
    "date": "2020-08-22",
    "value": -0.4947
  },
  {
    "date": "2020-08-23",
    "value": 1.4844
  },
  {
    "date": "2020-08-24",
    "value": 0.5768
  },
  {
    "date": "2020-08-25",
    "value": 3.6784
  },
  {
    "date": "2020-08-26",
    "value": 4.3883
  },
  {
    "date": "2020-08-27",
    "value": 3.2605
  },
  {
    "date": "2020-08-28",
    "value": -1.9127
  },
  {
    "date": "2020-08-29",
    "value": 0.6607
  },
  {
    "date": "2020-08-30",
    "value": 4.1378
  },
  {
    "date": "2020-08-31",
    "value": -1.2414
  },
  {
    "date": "2020-09-01",
    "value": 4.1534
  },
  {
    "date": "2020-09-02",
    "value": 5.627
  },
  {
    "date": "2020-09-03",
    "value": -3.5791
  },
  {
    "date": "2020-09-04",
    "value": 0.4772
  },
  {
    "date": "2020-09-05",
    "value": 3.0885
  },
  {
    "date": "2020-09-06",
    "value": 1.7958
  },
  {
    "date": "2020-09-07",
    "value": 1.4041
  },
  {
    "date": "2020-09-08",
    "value": 0.1512
  },
  {
    "date": "2020-09-09",
    "value": 2.2233
  },
  {
    "date": "2020-09-10",
    "value": 2.3506
  },
  {
    "date": "2020-09-11",
    "value": -2.8976
  },
  {
    "date": "2020-09-12",
    "value": -3.8234
  },
  {
    "date": "2020-09-13",
    "value": 1.9431
  },
  {
    "date": "2020-09-14",
    "value": -3.1353
  },
  {
    "date": "2020-09-15",
    "value": 3.0008
  },
  {
    "date": "2020-09-16",
    "value": 5.581
  },
  {
    "date": "2020-09-17",
    "value": 1.3292
  },
  {
    "date": "2020-09-18",
    "value": -5.3153
  },
  {
    "date": "2020-09-19",
    "value": 0.3306
  },
  {
    "date": "2020-09-20",
    "value": 1.979
  },
  {
    "date": "2020-09-21",
    "value": -3.3611
  },
  {
    "date": "2020-09-22",
    "value": -2.2171
  },
  {
    "date": "2020-09-23",
    "value": 1.1159
  },
  {
    "date": "2020-09-24",
    "value": -5.636
  },
  {
    "date": "2020-09-25",
    "value": -5.2687
  },
  {
    "date": "2020-09-26",
    "value": 7.4871
  },
  {
    "date": "2020-09-27",
    "value": 5.9208
  },
  {
    "date": "2020-09-28",
    "value": 1.1486
  },
  {
    "date": "2020-09-29",
    "value": 8.3868
  },
  {
    "date": "2020-09-30",
    "value": 3.0454
  },
  {
    "date": "2020-10-01",
    "value": -6.0618
  },
  {
    "date": "2020-10-02",
    "value": 8.1872
  },
  {
    "date": "2020-10-03",
    "value": -1.1544
  },
  {
    "date": "2020-10-04",
    "value": 0.2358
  },
  {
    "date": "2020-10-05",
    "value": -0.7698
  },
  {
    "date": "2020-10-06",
    "value": 2.7592
  },
  {
    "date": "2020-10-07",
    "value": 0.1554
  },
  {
    "date": "2020-10-08",
    "value": 0.0202
  },
  {
    "date": "2020-10-09",
    "value": 6.4017
  },
  {
    "date": "2020-10-10",
    "value": 2.4227
  },
  {
    "date": "2020-10-11",
    "value": 3.6751
  },
  {
    "date": "2020-10-12",
    "value": -2.4033
  },
  {
    "date": "2020-10-13",
    "value": -1.2656
  },
  {
    "date": "2020-10-14",
    "value": 1.9499
  },
  {
    "date": "2020-10-15",
    "value": 1.313
  },
  {
    "date": "2020-10-16",
    "value": 1.9821
  },
  {
    "date": "2020-10-17",
    "value": 0.348
  },
  {
    "date": "2020-10-18",
    "value": -5.0918
  },
  {
    "date": "2020-10-19",
    "value": 3.2759
  },
  {
    "date": "2020-10-20",
    "value": 6.7366
  },
  {
    "date": "2020-10-21",
    "value": 6.0979
  },
  {
    "date": "2020-10-22",
    "value": 6.0789
  },
  {
    "date": "2020-10-23",
    "value": -0.3985
  },
  {
    "date": "2020-10-24",
    "value": -1.2761
  },
  {
    "date": "2020-10-25",
    "value": 2.2433
  },
  {
    "date": "2020-10-26",
    "value": -3.2232
  },
  {
    "date": "2020-10-27",
    "value": 0.4185
  },
  {
    "date": "2020-10-28",
    "value": -1.1732
  },
  {
    "date": "2020-10-29",
    "value": -5.4156
  },
  {
    "date": "2020-10-30",
    "value": 2.8935
  },
  {
    "date": "2020-10-31",
    "value": 1.3839
  },
  {
    "date": "2020-11-01",
    "value": -2.5223
  },
  {
    "date": "2020-11-02",
    "value": 1.5089
  },
  {
    "date": "2020-11-03",
    "value": 3.8394
  },
  {
    "date": "2020-11-04",
    "value": 1.8291
  },
  {
    "date": "2020-11-05",
    "value": -1.0466
  },
  {
    "date": "2020-11-06",
    "value": -2.4718
  },
  {
    "date": "2020-11-07",
    "value": 2.6123
  },
  {
    "date": "2020-11-08",
    "value": 7.0646
  },
  {
    "date": "2020-11-09",
    "value": -0.791
  },
  {
    "date": "2020-11-10",
    "value": -1.2433
  },
  {
    "date": "2020-11-11",
    "value": -7.0048
  },
  {
    "date": "2020-11-12",
    "value": 2.3791
  },
  {
    "date": "2020-11-13",
    "value": 0.496
  },
  {
    "date": "2020-11-14",
    "value": 5.7931
  },
  {
    "date": "2020-11-15",
    "value": 2.4441
  },
  {
    "date": "2020-11-16",
    "value": 2.1887
  },
  {
    "date": "2020-11-17",
    "value": -1.3255
  },
  {
    "date": "2020-11-18",
    "value": 4.3121
  },
  {
    "date": "2020-11-19",
    "value": 0.2372
  },
  {
    "date": "2020-11-20",
    "value": -3.1924
  },
  {
    "date": "2020-11-21",
    "value": -3.6554
  },
  {
    "date": "2020-11-22",
    "value": 5.1269
  },
  {
    "date": "2020-11-23",
    "value": 1.3509
  },
  {
    "date": "2020-11-24",
    "value": -4.9057
  },
  {
    "date": "2020-11-25",
    "value": 1.6603
  },
  {
    "date": "2020-11-26",
    "value": 5.3457
  },
  {
    "date": "2020-11-27",
    "value": 3.9711
  },
  {
    "date": "2020-11-28",
    "value": -4.9538
  },
  {
    "date": "2020-11-29",
    "value": -1.561
  },
  {
    "date": "2020-11-30",
    "value": 2.9051
  },
  {
    "date": "2020-12-01",
    "value": -5.9592
  },
  {
    "date": "2020-12-02",
    "value": -5.4366
  },
  {
    "date": "2020-12-03",
    "value": -5.176
  },
  {
    "date": "2020-12-04",
    "value": -7.6254
  },
  {
    "date": "2020-12-05",
    "value": 1.8951
  },
  {
    "date": "2020-12-06",
    "value": 5.8665
  },
  {
    "date": "2020-12-07",
    "value": 1.7375
  },
  {
    "date": "2020-12-08",
    "value": 4.8457
  },
  {
    "date": "2020-12-09",
    "value": 0.759
  },
  {
    "date": "2020-12-10",
    "value": 0.1249
  },
  {
    "date": "2020-12-11",
    "value": -0.7779
  },
  {
    "date": "2020-12-12",
    "value": 1.4697
  },
  {
    "date": "2020-12-13",
    "value": -3.1058
  },
  {
    "date": "2020-12-14",
    "value": 2.2977
  },
  {
    "date": "2020-12-15",
    "value": 1.734
  },
  {
    "date": "2020-12-16",
    "value": 1.6641
  },
  {
    "date": "2020-12-17",
    "value": -4.2439
  },
  {
    "date": "2020-12-18",
    "value": 0.8295
  },
  {
    "date": "2020-12-19",
    "value": 4.7897
  },
  {
    "date": "2020-12-20",
    "value": 2.9168
  },
  {
    "date": "2020-12-21",
    "value": 4.2284
  },
  {
    "date": "2020-12-22",
    "value": -2.8582
  },
  {
    "date": "2020-12-23",
    "value": 1.0669
  },
  {
    "date": "2020-12-24",
    "value": -2.3373
  },
  {
    "date": "2020-12-25",
    "value": 3.3795
  },
  {
    "date": "2020-12-26",
    "value": -2.0349
  },
  {
    "date": "2020-12-27",
    "value": 3.4681
  },
  {
    "date": "2020-12-28",
    "value": 0.7296
  },
  {
    "date": "2020-12-29",
    "value": 1.9191
  },
  {
    "date": "2020-12-30",
    "value": -3.8806
  }
]