[
  {
    "date": "2020-01-01",
    "value": 6.0689
  },
  {
    "date": "2020-01-02",
    "value": 4.5189
  },
  {
    "date": "2020-01-03",
    "value": 6.6478
  },
  {
    "date": "2020-01-04",
    "value": 5.0741
  },
  {
    "date": "2020-01-05",
    "value": 3.6896
  },
  {
    "date": "2020-01-06",
    "value": 4.486
  },
  {
    "date": "2020-01-07",
    "value": 4.2186
  },
  {
    "date": "2020-01-08",
    "value": 3.2142
  },
  {
    "date": "2020-01-09",
    "value": 2.3664
  },
  {
    "date": "2020-01-10",
    "value": 7.8497
  },
  {
    "date": "2020-01-11",
    "value": 5.9978
  },
  {
    "date": "2020-01-12",
    "value": 6.2173
  },
  {
    "date": "2020-01-13",
    "value": 3.4948
  },
  {
    "date": "2020-01-14",
    "value": 3.8654
  },
  {
    "date": "2020-01-15",
    "value": 5.9194
  },
  {
    "date": "2020-01-16",
    "value": 1.0161
  },
  {
    "date": "2020-01-17",
    "value": 2.0157
  },
  {
    "date": "2020-01-18",
    "value": 4.6502
  },
  {
    "date": "2020-01-19",
    "value": 0.007
  },
  {
    "date": "2020-01-20",
    "value": 0.0123
  },
  {
    "date": "2020-01-21",
    "value": 7.7279
  },
  {
    "date": "2020-01-22",
    "value": 1.9746
  },
  {
    "date": "2020-01-23",
    "value": 6.3229
  },
  {
    "date": "2020-01-24",
    "value": 5.5078
  },
  {
    "date": "2020-01-25",
    "value": 7.4013
  },
  {
    "date": "2020-01-26",
    "value": 7.6172
  },
  {
    "date": "2020-01-27",
    "value": 2.5937
  },
  {
    "date": "2020-01-28",
    "value": 7.6295
  },
  {
    "date": "2020-01-29",
    "value": 3.9401
  },
  {
    "date": "2020-01-30",
    "value": 4.1897
  },
  {
    "date": "2020-01-31",
    "value": 2.1867
  },
  {
    "date": "2020-02-01",
    "value": 0.4635
  },
  {
    "date": "2020-02-02",
    "value": 5.0952
  },
  {
    "date": "2020-02-03",
    "value": 7.6238
  },
  {
    "date": "2020-02-04",
    "value": 3.4693
  },
  {
    "date": "2020-02-05",
    "value": 1.6529
  },
  {
    "date": "2020-02-06",
    "value": 5.0735
  },
  {
    "date": "2020-02-07",
    "value": 4.1065
  },
  {
    "date": "2020-02-08",
    "value": 3.0299
  },
  {
    "date": "2020-02-09",
    "value": 0.8191
  },
  {
    "date": "2020-02-10",
    "value": 0.9963
  },
  {
    "date": "2020-02-11",
    "value": 3.104
  },
  {
    "date": "2020-02-12",
    "value": 5.2115
  },
  {
    "date": "2020-02-13",
    "value": 7.5515
  },
  {
    "date": "2020-02-14",
    "value": 2.6833
  },
  {
    "date": "2020-02-15",
    "value": 5.0332
  },
  {
    "date": "2020-02-16",
    "value": 2.5154
  },
  {
    "date": "2020-02-17",
    "value": 7.8263
  },
  {
    "date": "2020-02-18",
    "value": 0.4634
  },
  {
    "date": "2020-02-19",
    "value": 4.2007
  },
  {
    "date": "2020-02-20",
    "value": 1.3555
  },
  {
    "date": "2020-02-21",
    "value": 1.8606
  },
  {
    "date": "2020-02-22",
    "value": 3.7369
  },
  {
    "date": "2020-02-23",
    "value": 6.6158
  },
  {
    "date": "2020-02-24",
    "value": 1.788
  },
  {
    "date": "2020-02-25",
    "value": 0.9135
  },
  {
    "date": "2020-02-26",
    "value": 3.6805
  },
  {
    "date": "2020-02-27",
    "value": 6.8652
  },
  {
    "date": "2020-02-28",
    "value": 5.7704
  },
  {
    "date": "2020-02-29",
    "value": 7.6149
  },
  {
    "date": "2020-03-01",
    "value": 7.6294
  },
  {
    "date": "2020-03-02",
    "value": 1.2047
  },
  {
    "date": "2020-03-03",
    "value": 2.8885
  },
  {
    "date": "2020-03-04",
    "value": 3.3459
  },
  {
    "date": "2020-03-05",
    "value": 5.5458
  },
  {
    "date": "2020-03-06",
    "value": 6.433
  },
  {
    "date": "2020-03-07",
    "value": 2.4751
  },
  {
    "date": "2020-03-08",
    "value": 1.3594
  },
  {
    "date": "2020-03-09",
    "value": 7.9477
  },
  {
    "date": "2020-03-10",
    "value": 1.5888
  },
  {
    "date": "2020-03-11",
    "value": 3.6629
  },
  {
    "date": "2020-03-12",
    "value": 1.5977
  },
  {
    "date": "2020-03-13",
    "value": 5.3981
  },
  {
    "date": "2020-03-14",
    "value": 6.9479
  },
  {
    "date": "2020-03-15",
    "value": 3.6841
  },
  {
    "date": "2020-03-16",
    "value": 0.7564
  },
  {
    "date": "2020-03-17",
    "value": 1.654
  },
  {
    "date": "2020-03-18",
    "value": 6.198
  },
  {
    "date": "2020-03-19",
    "value": 6.9282
  },
  {
    "date": "2020-03-20",
    "value": 2.5839
  },
  {
    "date": "2020-03-21",
    "value": 0.5158
  },
  {
    "date": "2020-03-22",
    "value": 7.3077
  },
  {
    "date": "2020-03-23",
    "value": 4.1013
  },
  {
    "date": "2020-03-24",
    "value": 1.5534
  },
  {
    "date": "2020-03-25",
    "value": 4.1642
  },
  {
    "date": "2020-03-26",
    "value": 3.3413
  },
  {
    "date": "2020-03-27",
    "value": 1.7774
  },
  {
    "date": "2020-03-28",
    "value": 1.5974
  },
  {
    "date": "2020-03-29",
    "value": 1.3627
  },
  {
    "date": "2020-03-30",
    "value": 5.5895
  },
  {
    "date": "2020-03-31",
    "value": 4.1569
  },
  {
    "date": "2020-04-01",
    "value": 6.073
  },
  {
    "date": "2020-04-02",
    "value": 4.1261
  },
  {
    "date": "2020-04-03",
    "value": 4.4357
  },
  {
    "date": "2020-04-04",
    "value": 3.9429
  },
  {
    "date": "2020-04-05",
    "value": 4.2814
  },
  {
    "date": "2020-04-06",
    "value": 3.8584
  },
  {
    "date": "2020-04-07",
    "value": 0.9581
  },
  {
    "date": "2020-04-08",
    "value": 6.6316
  },
  {
    "date": "2020-04-09",
    "value": 7.4458
  },
  {
    "date": "2020-04-10",
    "value": 3.1596
  },
  {
    "date": "2020-04-11",
    "value": 4.9589
  },
  {
    "date": "2020-04-12",
    "value": 3.3126
  },
  {
    "date": "2020-04-13",
    "value": 2.2141
  },
  {
    "date": "2020-04-14",
    "value": 7.2756
  },
  {
    "date": "2020-04-15",
    "value": 2.2842
  },
  {
    "date": "2020-04-16",
    "value": 2.6557
  },
  {
    "date": "2020-04-17",
    "value": 6.2683
  },
  {
    "date": "2020-04-18",
    "value": 3.7404
  },
  {
    "date": "2020-04-19",
    "value": 1.3219
  },
  {
    "date": "2020-04-20",
    "value": 5.0461
  },
  {
    "date": "2020-04-21",
    "value": 0.7949
  },
  {
    "date": "2020-04-22",
    "value": 5.4147
  },
  {
    "date": "2020-04-23",
    "value": 0.1428
  },
  {
    "date": "2020-04-24",
    "value": 2.5414
  },
  {
    "date": "2020-04-25",
    "value": 5.3445
  },
  {
    "date": "2020-04-26",
    "value": 7.7803
  },
  {
    "date": "2020-04-27",
    "value": 6.9664
  },
  {
    "date": "2020-04-28",
    "value": 6.2473
  },
  {
    "date": "2020-04-29",
    "value": 5.4557
  },
  {
    "date": "2020-04-30",
    "value": 2.6468
  },
  {
    "date": "2020-05-01",
    "value": 0.135
  },
  {
    "date": "2020-05-02",
    "value": 1.5326
  },
  {
    "date": "2020-05-03",
    "value": 1.0823
  },
  {
    "date": "2020-05-04",
    "value": 2.4344
  },
  {
    "date": "2020-05-05",
    "value": 0.7626
  },
  {
    "date": "2020-05-06",
    "value": 2.5239
  },
  {
    "date": "2020-05-07",
    "value": 3.1147
  },
  {
    "date": "2020-05-08",
    "value": 5.2983
  },
  {
    "date": "2020-05-09",
    "value": 1.6622
  },
  {
    "date": "2020-05-10",
    "value": 3.4698
  },
  {
    "date": "2020-05-11",
    "value": 0.7427
  },
  {
    "date": "2020-05-12",
    "value": 1.1664
  },
  {
    "date": "2020-05-13",
    "value": 6.4341
  },
  {
    "date": "2020-05-14",
    "value": 7.6687
  },
  {
    "date": "2020-05-15",
    "value": 4.7242
  },
  {
    "date": "2020-05-16",
    "value": 7.3692
  },
  {
    "date": "2020-05-17",
    "value": 5.3649
  },
  {
    "date": "2020-05-18",
    "value": 5.0887
  },
  {
    "date": "2020-05-19",
    "value": 3.1713
  },
  {
    "date": "2020-05-20",
    "value": 4.2589
  },
  {
    "date": "2020-05-21",
    "value": 4.8566
  },
  {
    "date": "2020-05-22",
    "value": 7.1494
  },
  {
    "date": "2020-05-23",
    "value": 4.2147
  },
  {
    "date": "2020-05-24",
    "value": 6.1665
  },
  {
    "date": "2020-05-25",
    "value": 5.919
  },
  {
    "date": "2020-05-26",
    "value": 3.056
  },
  {
    "date": "2020-05-27",
    "value": 6.3605
  },
  {
    "date": "2020-05-28",
    "value": 2.6788
  },
  {
    "date": "2020-05-29",
    "value": 1.3365
  },
  {
    "date": "2020-05-30",
    "value": 0.0825
  },
  {
    "date": "2020-05-31",
    "value": 5.9956
  },
  {
    "date": "2020-06-01",
    "value": 3.6465
  },
  {
    "date": "2020-06-02",
    "value": 5.9826
  },
  {
    "date": "2020-06-03",
    "value": 0.3917
  },
  {
    "date": "2020-06-04",
    "value": 1.0742
  },
  {
    "date": "2020-06-05",
    "value": 6.6118
  },
  {
    "date": "2020-06-06",
    "value": 6.8623
  },
  {
    "date": "2020-06-07",
    "value": 2.1995
  },
  {
    "date": "2020-06-08",
    "value": 7.0126
  },
  {
    "date": "2020-06-09",
    "value": 5.2752
  },
  {
    "date": "2020-06-10",
    "value": 7.5795
  },
  {
    "date": "2020-06-11",
    "value": 2.0988
  },
  {
    "date": "2020-06-12",
    "value": 5.2542
  },
  {
    "date": "2020-06-13",
    "value": 3.9675
  },
  {
    "date": "2020-06-14",
    "value": 6.7037
  },
  {
    "date": "2020-06-15",
    "value": 5.2352
  },
  {
    "date": "2020-06-16",
    "value": 4.7231
  },
  {
    "date": "2020-06-17",
    "value": 4.7816
  },
  {
    "date": "2020-06-18",
    "value": 2.022
  },
  {
    "date": "2020-06-19",
    "value": 3.116
  },
  {
    "date": "2020-06-20",
    "value": 4.1099
  },
  {
    "date": "2020-06-21",
    "value": 0.0092
  },
  {
    "date": "2020-06-22",
    "value": 6.0915
  },
  {
    "date": "2020-06-23",
    "value": 6.0468
  },
  {
    "date": "2020-06-24",
    "value": 5.7207
  },
  {
    "date": "2020-06-25",
    "value": 0.0108
  },
  {
    "date": "2020-06-26",
    "value": 2.0212
  },
  {
    "date": "2020-06-27",
    "value": 6.4203
  },
  {
    "date": "2020-06-28",
    "value": 4.8292
  },
  {
    "date": "2020-06-29",
    "value": 6.0455
  },
  {
    "date": "2020-06-30",
    "value": 6.8376
  },
  {
    "date": "2020-07-01",
    "value": 1.409
  },
  {
    "date": "2020-07-02",
    "value": 1.8821
  },
  {
    "date": "2020-07-03",
    "value": 1.4858
  },
  {
    "date": "2020-07-04",
    "value": 0.916
  },
  {
    "date": "2020-07-05",
    "value": 4.1815
  },
  {
    "date": "2020-07-06",
    "value": 3.9392
  },
  {
    "date": "2020-07-07",
    "value": 7.981
  },
  {
    "date": "2020-07-08",
    "value": 3.7533
  },
  {
    "date": "2020-07-09",
    "value": 4.6209
  },
  {
    "date": "2020-07-10",
    "value": 6.0991
  },
  {
    "date": "2020-07-11",
    "value": 1.9674
  },
  {
    "date": "2020-07-12",
    "value": 6.887
  },
  {
    "date": "2020-07-13",
    "value": 5.6544
  },
  {
    "date": "2020-07-14",
    "value": 3.7832
  },
  {
    "date": "2020-07-15",
    "value": 0.2099
  },
  {
    "date": "2020-07-16",
    "value": 6.2266
  },
  {
    "date": "2020-07-17",
    "value": 2.9621
  },
  {
    "date": "2020-07-18",
    "value": 5.2281
  },
  {
    "date": "2020-07-19",
    "value": 4.9005
  },
  {
    "date": "2020-07-20",
    "value": 2.8916
  },
  {
    "date": "2020-07-21",
    "value": 4.608
  },
  {
    "date": "2020-07-22",
    "value": 6.7123
  },
  {
    "date": "2020-07-23",
    "value": 3.5748
  },
  {
    "date": "2020-07-24",
    "value": 5.5584
  },
  {
    "date": "2020-07-25",
    "value": 3.6385
  },
  {
    "date": "2020-07-26",
    "value": 3.2987
  },
  {
    "date": "2020-07-27",
    "value": 0.2876
  },
  {
    "date": "2020-07-28",
    "value": 7.1743
  },
  {
    "date": "2020-07-29",
    "value": 0.7083
  },
  {
    "date": "2020-07-30",
    "value": 7.0574
  },
  {
    "date": "2020-07-31",
    "value": 4.554
  },
  {
    "date": "2020-08-01",
    "value": 7.3211
  },
  {
    "date": "2020-08-02",
    "value": 4.2034
  },
  {
    "date": "2020-08-03",
    "value": 5.8045
  },
  {
    "date": "2020-08-04",
    "value": 6.5225
  },
  {
    "date": "2020-08-05",
    "value": 1.4777
  },
  {
    "date": "2020-08-06",
    "value": 3.9525
  },
  {
    "date": "2020-08-07",
    "value": 0.1649
  },
  {
    "date": "2020-08-08",
    "value": 7.5637
  },
  {
    "date": "2020-08-09",
    "value": 6.7476
  },
  {
    "date": "2020-08-10",
    "value": 4.5642
  },
  {
    "date": "2020-08-11",
    "value": 1.9929
  },
  {
    "date": "2020-08-12",
    "value": 4.5066
  },
  {
    "date": "2020-08-13",
    "value": 5.9965
  },
  {
    "date": "2020-08-14",
    "value": 0.9738
  },
  {
    "date": "2020-08-15",
    "value": 1.3092
  },
  {
    "date": "2020-08-16",
    "value": 6.8567
  },
  {
    "date": "2020-08-17",
    "value": 3.6904
  },
  {
    "date": "2020-08-18",
    "value": 5.4932
  },
  {
    "date": "2020-08-19",
    "value": 4.2374
  },
  {
    "date": "2020-08-20",
    "value": 4.2261
  },
  {
    "date": "2020-08-21",
    "value": 5.1561
  },
  {
    "date": "2020-08-22",
    "value": 2.2679
  },
  {
    "date": "2020-08-23",
    "value": 6.3507
  },
  {
    "date": "2020-08-24",
    "value": 2.6623
  },
  {
    "date": "2020-08-25",
    "value": 5.5855
  },
  {
    "date": "2020-08-26",
    "value": 4.5091
  },
  {
    "date": "2020-08-27",
    "value": 5.466
  },
  {
    "date": "2020-08-28",
    "value": 1.3355
  },
  {
    "date": "2020-08-29",
    "value": 4.0788
  },
  {
    "date": "2020-08-30",
    "value": 4.0543
  },
  {
    "date": "2020-08-31",
    "value": 7.6798
  },
  {
    "date": "2020-09-01",
    "value": 1.335
  },
  {
    "date": "2020-09-02",
    "value": 5.9847
  },
  {
    "date": "2020-09-03",
    "value": 1.9212
  },
  {
    "date": "2020-09-04",
    "value": 3.5603
  },
  {
    "date": "2020-09-05",
    "value": 0.6038
  },
  {
    "date": "2020-09-06",
    "value": 0.0546
  },
  {
    "date": "2020-09-07",
    "value": 1.0465
  },
  {
    "date": "2020-09-08",
    "value": 5.4077
  },
  {
    "date": "2020-09-09",
    "value": 6.7671
  },
  {
    "date": "2020-09-10",
    "value": 4.5502
  },
  {
    "date": "2020-09-11",
    "value": 7.248
  },
  {
    "date": "2020-09-12",
    "value": 1.9597
  },
  {
    "date": "2020-09-13",
    "value": 2.354
  },
  {
    "date": "2020-09-14",
    "value": 5.2788
  },
  {
    "date": "2020-09-15",
    "value": 2.4436
  },
  {
    "date": "2020-09-16",
    "value": 3.9937
  },
  {
    "date": "2020-09-17",
    "value": 4.6359
  },
  {
    "date": "2020-09-18",
    "value": 6.2285
  },
  {
    "date": "2020-09-19",
    "value": 5.0166
  },
  {
    "date": "2020-09-20",
    "value": 4.274
  },
  {
    "date": "2020-09-21",
    "value": 2.9141
  },
  {
    "date": "2020-09-22",
    "value": 0.3197
  },
  {
    "date": "2020-09-23",
    "value": 1.1533
  },
  {
    "date": "2020-09-24",
    "value": 4.8795
  },
  {
    "date": "2020-09-25",
    "value": 4.8641
  },
  {
    "date": "2020-09-26",
    "value": 3.031
  },
  {
    "date": "2020-09-27",
    "value": 7.2182
  },
  {
    "date": "2020-09-28",
    "value": 5.2397
  },
  {
    "date": "2020-09-29",
    "value": 4.4831
  },
  {
    "date": "2020-09-30",
    "value": 3.3082
  },
  {
    "date": "2020-10-01",
    "value": 6.2446
  },
  {
    "date": "2020-10-02",
    "value": 6.0078
  },
  {
    "date": "2020-10-03",
    "value": 6.3657
  },
  {
    "date": "2020-10-04",
    "value": 3.44
  },
  {
    "date": "2020-10-05",
    "value": 0.6571
  },
  {
    "date": "2020-10-06",
    "value": 0.2126
  },
  {
    "date": "2020-10-07",
    "value": 4.1555
  },
  {
    "date": "2020-10-08",
    "value": 4.696
  },
  {
    "date": "2020-10-09",
    "value": 4.5709
  },
  {
    "date": "2020-10-10",
    "value": 6.7582
  },
  {
    "date": "2020-10-11",
    "value": 6.9906
  },
  {
    "date": "2020-10-12",
    "value": 5.1911
  },
  {
    "date": "2020-10-13",
    "value": 1.5517
  },
  {
    "date": "2020-10-14",
    "value": 1.5846
  },
  {
    "date": "2020-10-15",
    "value": 0.7023
  },
  {
    "date": "2020-10-16",
    "value": 7.1827
  },
  {
    "date": "2020-10-17",
    "value": 3.2049
  },
  {
    "date": "2020-10-18",
    "value": 3.9188
  },
  {
    "date": "2020-10-19",
    "value": 7.1959
  },
  {
    "date": "2020-10-20",
    "value": 3.9431
  },
  {
    "date": "2020-10-21",
    "value": 5.6092
  },
  {
    "date": "2020-10-22",
    "value": 2.7665
  },
  {
    "date": "2020-10-23",
    "value": 7.1862
  },
  {
    "date": "2020-10-24",
    "value": 6.8957
  },
  {
    "date": "2020-10-25",
    "value": 1.1445
  },
  {
    "date": "2020-10-26",
    "value": 5.8618
  },
  {
    "date": "2020-10-27",
    "value": 3.7054
  },
  {
    "date": "2020-10-28",
    "value": 1.525
  },
  {
    "date": "2020-10-29",
    "value": 4.5182
  },
  {
    "date": "2020-10-30",
    "value": 0.1077
  },
  {
    "date": "2020-10-31",
    "value": 4.8724
  },
  {
    "date": "2020-11-01",
    "value": 5.841
  },
  {
    "date": "2020-11-02",
    "value": 5.6429
  },
  {
    "date": "2020-11-03",
    "value": 2.5372
  },
  {
    "date": "2020-11-04",
    "value": 4.4426
  },
  {
    "date": "2020-11-05",
    "value": 0.1093
  },
  {
    "date": "2020-11-06",
    "value": 0.6091
  },
  {
    "date": "2020-11-07",
    "value": 7.2414
  },
  {
    "date": "2020-11-08",
    "value": 7.8736
  },
  {
    "date": "2020-11-09",
    "value": 2.6351
  },
  {
    "date": "2020-11-10",
    "value": 5.1904
  },
  {
    "date": "2020-11-11",
    "value": 3.8632
  },
  {
    "date": "2020-11-12",
    "value": 5.0956
  },
  {
    "date": "2020-11-13",
    "value": 6.1086
  },
  {
    "date": "2020-11-14",
    "value": 5.1907
  },
  {
    "date": "2020-11-15",
    "value": 2.1677
  },
  {
    "date": "2020-11-16",
    "value": 0.1029
  },
  {
    "date": "2020-11-17",
    "value": 6.1613
  },
  {
    "date": "2020-11-18",
    "value": 4.184
  },
  {
    "date": "2020-11-19",
    "value": 5.3682
  },
  {
    "date": "2020-11-20",
    "value": 1.2805
  },
  {
    "date": "2020-11-21",
    "value": 2.0571
  },
  {
    "date": "2020-11-22",
    "value": 3.6384
  },
  {
    "date": "2020-11-23",
    "value": 6.1198
  },
  {
    "date": "2020-11-24",
    "value": 0.3748
  },
  {
    "date": "2020-11-25",
    "value": 6.4752
  },
  {
    "date": "2020-11-26",
    "value": 5.4257
  },
  {
    "date": "2020-11-27",
    "value": 2.9732
  },
  {
    "date": "2020-11-28",
    "value": 0.5822
  },
  {
    "date": "2020-11-29",
    "value": 6.247
  },
  {
    "date": "2020-11-30",
    "value": 5.3143
  },
  {
    "date": "2020-12-01",
    "value": 0.0492
  },
  {
    "date": "2020-12-02",
    "value": 7.7143
  },
  {
    "date": "2020-12-03",
    "value": 3.6411
  },
  {
    "date": "2020-12-04",
    "value": 2.6042
  },
  {
    "date": "2020-12-05",
    "value": 4.5644
  },
  {
    "date": "2020-12-06",
    "value": 5.4551
  },
  {
    "date": "2020-12-07",
    "value": 1.9105
  },
  {
    "date": "2020-12-08",
    "value": 5.1728
  },
  {
    "date": "2020-12-09",
    "value": 6.9717
  },
  {
    "date": "2020-12-10",
    "value": 4.9125
  },
  {
    "date": "2020-12-11",
    "value": 0.5261
  },
  {
    "date": "2020-12-12",
    "value": 3.0094
  },
  {
    "date": "2020-12-13",
    "value": 2.5337
  },
  {
    "date": "2020-12-14",
    "value": 5.2181
  },
  {
    "date": "2020-12-15",
    "value": 0.5235
  },
  {
    "date": "2020-12-16",
    "value": 0.7782
  },
  {
    "date": "2020-12-17",
    "value": 3.2615
  },
  {
    "date": "2020-12-18",
    "value": 2.7806
  },
  {
    "date": "2020-12-19",
    "value": 0.6977
  },
  {
    "date": "2020-12-20",
    "value": 0.796
  },
  {
    "date": "2020-12-21",
    "value": 1.9949
  },
  {
    "date": "2020-12-22",
    "value": 5.1776
  },
  {
    "date": "2020-12-23",
    "value": 0.5072
  },
  {
    "date": "2020-12-24",
    "value": 1.3166
  },
  {
    "date": "2020-12-25",
    "value": 2.9461
  },
  {
    "date": "2020-12-26",
    "value": 4.4084
  },
  {
    "date": "2020-12-27",
    "value": 3.7358
  },
  {
    "date": "2020-12-28",
    "value": 1.6704
  },
  {
    "date": "2020-12-29",
    "value": 7.9464
  },
  {
    "date": "2020-12-30",
    "value": 6.3501
  }
]